stix2patterns/__init__.py
stix2patterns/exceptions.py
stix2patterns/helpers.py
stix2patterns/inspector.py
stix2patterns/pattern.py
stix2patterns/validator.py
stix2patterns/grammars/STIXPatternLexer.py
stix2patterns/grammars/STIXPatternListener.py
stix2patterns/grammars/STIXPatternParser.py
stix2patterns/grammars/STIXPatternVisitor.py
stix2patterns/grammars/__init__.py
stix2patterns/test/__init__.py
stix2patterns/test/test_helpers.py
stix2patterns/test/v20/__init__.py
stix2patterns/test/v20/spec_examples.txt
stix2patterns/test/v20/test_inspector.py
stix2patterns/test/v20/test_validator.py
stix2patterns/test/v21/__init__.py
stix2patterns/test/v21/spec_examples.txt
stix2patterns/test/v21/test_inspector.py
stix2patterns/test/v21/test_validator.py
stix2patterns/v20/__init__.py
stix2patterns/v20/inspector.py
stix2patterns/v20/object_validator.py
stix2patterns/v20/pattern.py
stix2patterns/v20/validator.py
stix2patterns/v20/grammars/STIXPatternLexer.py
stix2patterns/v20/grammars/STIXPatternListener.py
stix2patterns/v20/grammars/STIXPatternParser.py
stix2patterns/v20/grammars/STIXPatternVisitor.py
stix2patterns/v20/grammars/__init__.py
stix2patterns/v21/__init__.py
stix2patterns/v21/inspector.py
stix2patterns/v21/object_validator.py
stix2patterns/v21/pattern.py
stix2patterns/v21/validator.py
stix2patterns/v21/grammars/STIXPatternLexer.py
stix2patterns/v21/grammars/STIXPatternListener.py
stix2patterns/v21/grammars/STIXPatternParser.py
stix2patterns/v21/grammars/STIXPatternVisitor.py
stix2patterns/v21/grammars/__init__.py
stix2_patterns-1.3.2.dist-info/LICENSE
stix2_patterns-1.3.2.dist-info/METADATA
stix2_patterns-1.3.2.dist-info/WHEEL
stix2_patterns-1.3.2.dist-info/entry_points.txt
stix2_patterns-1.3.2.dist-info/top_level.txt
stix2_patterns-1.3.2.dist-info/RECORD
