Metadata-Version: 2.1
Name: stix2-patterns
Version: 1.3.2
Summary: Validate STIX 2 Patterns.
Home-page: https://github.com/oasis-open/cti-pattern-validator
Author: OASIS Cyber Threat Intelligence Technical Committee
Author-email: cti-users@lists.oasis-open.org
Maintainer: Chris Lenk
Maintainer-email: clenk@mitre.org
License: UNKNOWN
Platform: UNKNOWN
Classifier: Development Status :: 3 - Alpha
Classifier: License :: OSI Approved :: BSD License
Classifier: Programming Language :: Python :: 2
Classifier: Programming Language :: Python :: 2.7
Classifier: Programming Language :: Python :: 3
Classifier: Programming Language :: Python :: 3.4
Classifier: Programming Language :: Python :: 3.5
Classifier: Programming Language :: Python :: 3.6
Classifier: Programming Language :: Python :: 3.7
Provides-Extra: dev
Provides-Extra: docs
Provides-Extra: test
